django_app_logs/__init__.py
django_app_logs/admin.py
django_app_logs/apps.py
django_app_logs/middleware.py
django_app_logs/models.py
django_app_logs/registry.py
django_app_logs/serializers.py
django_app_logs/signals.py
django_app_logs/utils.py
django_app_logs/migrations/0001_initial.py
django_app_logs/migrations/__init__.py
django_app_logs/templates/admin/history/object_history.html
django_app_logs/templates/admin/partials/action_view.html
django_app_logs-2.6.1.dist-info/METADATA
django_app_logs-2.6.1.dist-info/WHEEL
django_app_logs-2.6.1.dist-info/top_level.txt
django_app_logs-2.6.1.dist-info/RECORD
